{
  "en": {
    "languageLabel": "Language",
    "english": "English",
    "spanish": "Spanish",
    "appTitle": "Papelitos",
    "participantPrompt": "Insert a participant name:",
    "participantPlaceholder": "insert a name",
    "addButton": "Add",
    "straggleButton": "Straggle",
    "addStragglerToParticipants": "Move straggler to participants",
    "moveStragglerToParticipants": "Move {name} to participants",
    "moveStragglerUp": "Move {name} up",
    "moveStragglerDown": "Move {name} down",
    "editStraggler": "Edit straggler {name}",
    "removeStraggler": "Remove straggler {name}",
    "editButton": "Edit",
    "settingsLabel": "Settings",
    "configurationTitle": "Configuration",
    "closeDialog": "Close dialog",
    "doneButton": "Done",
    "selectLanguage": "Select language",
    "suspenseLabel": "Suspense",
    "suspenseToggleLabel": "Toggle suspense mode",
    "stragglersToggleLabel": "Toggle stragglers",
    "versionLabel": "Version",
    "countdownButton": "{seconds}s",
    "countdownMessage": "Shuffling in {seconds} seconds...",
    "duplicateParticipant": "{name} already exists.",
    "participantsTitle": "Participants",
    "stragglersTitle": "Stragglers",
    "emptyParticipants": "Add participants to start the raffle.",
    "shuffleButton": "Shuffle",
    "clearButton": "Clear list",
    "visitLink": "Visit Tato",
    "views": "views",
    "editParticipant": "Edit participant",
    "removeParticipant": "Remove participant"
  },
  "es": {
    "languageLabel": "Idioma",
    "english": "Ingl\u00e9s",
    "spanish": "Espa\u00f1ol",
    "appTitle": "Papelitos",
    "participantPrompt": "Ingresa el nombre de un participante:",
    "participantPlaceholder": "ingresa un nombre",
    "addButton": "Agregar",
    "straggleButton": "Rezagar",
    "addStragglerToParticipants": "Mover rezagado a participantes",
    "moveStragglerToParticipants": "Mover {name} a participantes",
    "moveStragglerUp": "Mover {name} hacia arriba",
    "moveStragglerDown": "Mover {name} hacia abajo",
    "editStraggler": "Editar rezagado {name}",
    "removeStraggler": "Eliminar rezagado {name}",
    "editButton": "Editar",
    "settingsLabel": "Configuracion",
    "configurationTitle": "Configuracion",
    "closeDialog": "Cerrar dialogo",
    "doneButton": "Listo",
    "selectLanguage": "Seleccionar idioma",
    "suspenseLabel": "Suspenso",
    "suspenseToggleLabel": "Activar suspenso",
    "stragglersToggleLabel": "Activar rezagados",
    "versionLabel": "Version",
    "countdownButton": "{seconds}s",
    "countdownMessage": "Mezclando en {seconds} segundos...",
    "duplicateParticipant": "{name} ya existe.",
    "participantsTitle": "Participantes",
    "stragglersTitle": "Rezagados",
    "emptyParticipants": "Agrega participantes para iniciar el sorteo.",
    "shuffleButton": "Mezclar",
    "clearButton": "Limpiar lista",
    "visitLink": "Visitar a Tato",
    "views": "visitas",
    "editParticipant": "Editar participante",
    "removeParticipant": "Eliminar participante"
  }
}
